reswatch/__init__.py
reswatch/main.py
reswatch/profiler.py
reswatch-0.1.1.dist-info/METADATA
reswatch-0.1.1.dist-info/WHEEL
reswatch-0.1.1.dist-info/RECORD
