Metadata-Version: 2.1
Name: reswatch
Version: 0.1.1
Summary: 
Author: Gaoshan Deng
Author-email: gaoshan.deng@foxmail.com
Requires-Python: >=3.8,<4.0
Classifier: Programming Language :: Python :: 3
Classifier: Programming Language :: Python :: 3.8
Classifier: Programming Language :: Python :: 3.9
Classifier: Programming Language :: Python :: 3.10
Classifier: Programming Language :: Python :: 3.11
Classifier: Programming Language :: Python :: 3.12
Requires-Dist: psutil (>=5.9.7,<6.0.0)
